shinehope/__init__.py
shinehope/eaaccess/__init__.py
shinehope/eaaccess/appbacktest.py
shinehope/eaaccess/apptrade.py
shinehope/eaaccess/backtest.py
shinehope/eaaccess/broker.py
shinehope/eaaccess/candlestick.py
shinehope/eaaccess/constants.py
shinehope/eaaccess/globalvars.py
shinehope/eaaccess/marketdata.py
shinehope/eaaccess/settings.py
shinehope/eaaccess/dataaccess/__init__.py
shinehope/eaaccess/dataaccess/klinestream.py
shinehope/eaaccess/dataaccess/sqlite.py
shinehope/eaaccess/importers/__init__.py
shinehope/eaaccess/importers/klineimport.py
shinehope/eaaccess/importers/brokers/__init__.py
shinehope/eaaccess/importers/brokers/importer.py
shinehope/eaaccess/strategy/__init__.py
shinehope/eaaccess/strategy/indicator.py
shinehope/eaaccess/strategy/strategy.py
shinehope/eaminer/EACtrl.py
shinehope/eaminer/EAInfo.py
shinehope/eaminer/MinerTalk.py
shinehope/eaminer/__init__.py
shinehope/utils/MinerFunc.py
shinehope/utils/__init__.py
shinehope/utils/definitions.py
shinehope/utils/myfunc.py
shinehope/utils/mylogger.py
eaaccess_crypto-0.5.1.dist-info/LICENSE
eaaccess_crypto-0.5.1.dist-info/METADATA
eaaccess_crypto-0.5.1.dist-info/WHEEL
eaaccess_crypto-0.5.1.dist-info/top_level.txt
eaaccess_crypto-0.5.1.dist-info/RECORD
