Metadata-Version: 2.1
Name: eaaccess-crypto
Version: 0.5.1
Summary: A cryptocurrency trading platform
Home-page: UNKNOWN
Author: Jinn Lin
Author-email: linhj0313@gmail.com
License: UNKNOWN
Platform: UNKNOWN
Classifier: Programming Language :: Python :: 3
Classifier: License :: OSI Approved :: MIT License
Classifier: Operating System :: OS Independent
Requires-Python: >=3.6
